tuprolog/__init__.py
tuprolog/__main__.py
tuprolog/jvmioutils.py
tuprolog/jvmutils.py
tuprolog/pyutils.py
tuprolog/core/__init__.py
tuprolog/core/_ktadapt.py
tuprolog/core/_ktmath.py
tuprolog/core/comparators.py
tuprolog/core/formatters.py
tuprolog/core/visitors.py
tuprolog/core/exception/__init__.py
tuprolog/core/exception/_ktadapt.py
tuprolog/core/operators/__init__.py
tuprolog/core/operators/_ktadapt.py
tuprolog/core/parsing/__init__.py
tuprolog/core/parsing/_ktadapt.py
tuprolog/libs/2p-0.20.8-full.jar
tuprolog/libs/__init__.py
tuprolog/solve/__init__.py
tuprolog/solve/_ktadapt.py
tuprolog/solve/channel/__init__.py
tuprolog/solve/classic/__init__.py
tuprolog/solve/data/__init__.py
tuprolog/solve/exception/__init__.py
tuprolog/solve/exception/error/__init__.py
tuprolog/solve/exception/error/domain/__init__.py
tuprolog/solve/exception/error/evaluation/__init__.py
tuprolog/solve/exception/error/existence/__init__.py
tuprolog/solve/exception/error/instantiation/__init__.py
tuprolog/solve/exception/error/message/__init__.py
tuprolog/solve/exception/error/permission/__init__.py
tuprolog/solve/exception/error/representation/__init__.py
tuprolog/solve/exception/error/syntax/__init__.py
tuprolog/solve/exception/error/system/__init__.py
tuprolog/solve/exception/error/type/__init__.py
tuprolog/solve/exception/warning/__init__.py
tuprolog/solve/flags/__init__.py
tuprolog/solve/function/__init__.py
tuprolog/solve/library/__init__.py
tuprolog/solve/library/exception/__init__.py
tuprolog/solve/plp/__init__.py
tuprolog/solve/primitive/__init__.py
tuprolog/solve/problog/__init__.py
tuprolog/solve/problog/operators.py
tuprolog/solve/prolog/__init__.py
tuprolog/solve/sideffcts/__init__.py
tuprolog/solve/stdlib/__init__.py
tuprolog/solve/stdlib/function/__init__.py
tuprolog/solve/stdlib/primitive/__init__.py
tuprolog/solve/stdlib/rule/__init__.py
tuprolog/theory/__init__.py
tuprolog/theory/_ktadapt.py
tuprolog/theory/parsing/__init__.py
tuprolog/theory/parsing/_ktadapt.py
2ppy-0.4.1.dist-info/LICENSE
2ppy-0.4.1.dist-info/METADATA
2ppy-0.4.1.dist-info/WHEEL
2ppy-0.4.1.dist-info/top_level.txt
2ppy-0.4.1.dist-info/RECORD
