Metadata-Version: 2.1
Name: 2ppy
Version: 0.4.1
Summary: Python-based implementation of tuProlog -- the open ecosystem for symbolic AI --, based on 2P-Kt
Home-page: https://github.com/tuProlog/2ppy
Author: Giovanni Ciatto
Author-email: giovanni.ciatto@unibo.it
License: Apache 2.0 License
Project-URL: Bug Reports, https://github.com/tuProlog/2ppy/issues
Project-URL: Source, https://github.com/tuProlog/2ppy
Keywords: prolog,symbolic ai,ecosystem,tuprolog,2p,python
Platform: Independant
Classifier: Development Status :: 3 - Alpha
Classifier: Intended Audience :: Developers
Classifier: Topic :: Software Development :: Interpreters
Classifier: Topic :: Software Development :: Libraries
Classifier: Topic :: Scientific/Engineering :: Artificial Intelligence
Classifier: License :: OSI Approved :: Apache Software License
Classifier: Programming Language :: Python :: 3
Classifier: Programming Language :: Python :: 3.6
Classifier: Programming Language :: Python :: 3.7
Classifier: Programming Language :: Python :: 3.8
Classifier: Programming Language :: Python :: 3.9
Classifier: Programming Language :: Python :: 3 :: Only
Classifier: Programming Language :: Prolog
Requires-Python: >=3.6, <4
License-File: LICENSE
Requires-Dist: JPype1==1.5.0
